Workbook

Sheet Assumptions
B1: REVENUE ASSUMPTIONS
B3: RETAINER CLIENTS
B4: Essential clients (qty) | C4: 2 | D4: ← adjust this
B5: Advanced clients (qty) | C5: 1 | D5: ← adjust this
B6: Premium clients (qty) | C6: 2 | D6: ← adjust this
B7: Master clients (qty) | C7: 0 | D7: ← adjust this
B9: RETAINER PRICES / MONTH
B10: Essential price | C10: 400 | D10: ← adjust this
B11: Advanced price | C11: 800 | D11: ← adjust this
B12: Premium price | C12: 1050 | D12: ← adjust this
B13: Master price | C13: 1500 | D13: ← adjust this
B15: ONE-OFF PROJECTS
B16: Sprint projects / month | C16: 2 | D16: ← adjust this
B17: Sprint avg price | C17: 500 | D17: ← adjust this
B18: Campaign projects / month | C18: 1 | D18: ← adjust this
B19: Campaign avg price | C19: 1200 | D19: ← adjust this
B21: GOALS
B22: Monthly revenue target | C22: 5000 | D22: ← adjust this
B23: Annual revenue target | C23: =B23*12 | D23: ← adjust this
B24: Est. profit margin | C24: 0.85 | D24: ← adjust this

Sheet Monthly Projection
B1: Month | C1: Retainer Revenue | D1: Sprint Revenue | E1: Campaign Revenue | F1: Total Revenue | G1: Monthly Target | H1: vs Target ($) | I1: vs Target (%)
B2: January | C2: =Assumptions!C5*Assumptions!C11+Assumptions!C6*Assumptions!C12+Assumptions!C7*Assumptions!C13+Assumptions!C8*Assumptions!C14 | D2: =Assumptions!C17*Assumptions!C18 | E2: =Assumptions!C19*Assumptions!C20 | F2: =C2+D2+E2 | G2: =Assumptions!C23 | H2: =F2-G2 | I2: =IF(G2=0,"",F2/G2-1)
B3: February | C3: =Assumptions!C5*Assumptions!C11+Assumptions!C6*Assumptions!C12+Assumptions!C7*Assumptions!C13+Assumptions!C8*Assumptions!C14 | D3: =Assumptions!C17*Assumptions!C18 | E3: =Assumptions!C19*Assumptions!C20 | F3: =C3+D3+E3 | G3: =Assumptions!C23 | H3: =F3-G3 | I3: =IF(G3=0,"",F3/G3-1)
B4: March | C4: =Assumptions!C5*Assumptions!C11+Assumptions!C6*Assumptions!C12+Assumptions!C7*Assumptions!C13+Assumptions!C8*Assumptions!C14 | D4: =Assumptions!C17*Assumptions!C18 | E4: =Assumptions!C19*Assumptions!C20 | F4: =C4+D4+E4 | G4: =Assumptions!C23 | H4: =F4-G4 | I4: =IF(G4=0,"",F4/G4-1)
B5: April | C5: =Assumptions!C5*Assumptions!C11+Assumptions!C6*Assumptions!C12+Assumptions!C7*Assumptions!C13+Assumptions!C8*Assumptions!C14 | D5: =Assumptions!C17*Assumptions!C18 | E5: =Assumptions!C19*Assumptions!C20 | F5: =C5+D5+E5 | G5: =Assumptions!C23 | H5: =F5-G5 | I5: =IF(G5=0,"",F5/G5-1)
B6: May | C6: =Assumptions!C5*Assumptions!C11+Assumptions!C6*Assumptions!C12+Assumptions!C7*Assumptions!C13+Assumptions!C8*Assumptions!C14 | D6: =Assumptions!C17*Assumptions!C18 | E6: =Assumptions!C19*Assumptions!C20 | F6: =C6+D6+E6 | G6: =Assumptions!C23 | H6: =F6-G6 | I6: =IF(G6=0,"",F6/G6-1)
B7: June | C7: =Assumptions!C5*Assumptions!C11+Assumptions!C6*Assumptions!C12+Assumptions!C7*Assumptions!C13+Assumptions!C8*Assumptions!C14 | D7: =Assumptions!C17*Assumptions!C18 | E7: =Assumptions!C19*Assumptions!C20 | F7: =C7+D7+E7 | G7: =Assumptions!C23 | H7: =F7-G7 | I7: =IF(G7=0,"",F7/G7-1)
B8: July | C8: =Assumptions!C5*Assumptions!C11+Assumptions!C6*Assumptions!C12+Assumptions!C7*Assumptions!C13+Assumptions!C8*Assumptions!C14 | D8: =Assumptions!C17*Assumptions!C18 | E8: =Assumptions!C19*Assumptions!C20 | F8: =C8+D8+E8 | G8: =Assumptions!C23 | H8: =F8-G8 | I8: =IF(G8=0,"",F8/G8-1)
B9: August | C9: =Assumptions!C5*Assumptions!C11+Assumptions!C6*Assumptions!C12+Assumptions!C7*Assumptions!C13+Assumptions!C8*Assumptions!C14 | D9: =Assumptions!C17*Assumptions!C18 | E9: =Assumptions!C19*Assumptions!C20 | F9: =C9+D9+E9 | G9: =Assumptions!C23 | H9: =F9-G9 | I9: =IF(G9=0,"",F9/G9-1)
B10: September | C10: =Assumptions!C5*Assumptions!C11+Assumptions!C6*Assumptions!C12+Assumptions!C7*Assumptions!C13+Assumptions!C8*Assumptions!C14 | D10: =Assumptions!C17*Assumptions!C18 | E10: =Assumptions!C19*Assumptions!C20 | F10: =C10+D10+E10 | G10: =Assumptions!C23 | H10: =F10-G10 | I10: =IF(G10=0,"",F10/G10-1)
B11: October | C11: =Assumptions!C5*Assumptions!C11+Assumptions!C6*Assumptions!C12+Assumptions!C7*Assumptions!C13+Assumptions!C8*Assumptions!C14 | D11: =Assumptions!C17*Assumptions!C18 | E11: =Assumptions!C19*Assumptions!C20 | F11: =C11+D11+E11 | G11: =Assumptions!C23 | H11: =F11-G11 | I11: =IF(G11=0,"",F11/G11-1)
B12: November | C12: =Assumptions!C5*Assumptions!C11+Assumptions!C6*Assumptions!C12+Assumptions!C7*Assumptions!C13+Assumptions!C8*Assumptions!C14 | D12: =Assumptions!C17*Assumptions!C18 | E12: =Assumptions!C19*Assumptions!C20 | F12: =C12+D12+E12 | G12: =Assumptions!C23 | H12: =F12-G12 | I12: =IF(G12=0,"",F12/G12-1)
B13: December | C13: =Assumptions!C5*Assumptions!C11+Assumptions!C6*Assumptions!C12+Assumptions!C7*Assumptions!C13+Assumptions!C8*Assumptions!C14 | D13: =Assumptions!C17*Assumptions!C18 | E13: =Assumptions!C19*Assumptions!C20 | F13: =C13+D13+E13 | G13: =Assumptions!C23 | H13: =F13-G13 | I13: =IF(G13=0,"",F13/G13-1)
B15: ANNUAL TOTALS | C15: =SUM(C2:C13) | D15: =SUM(D2:D13) | E15: =SUM(E2:E13) | F15: =SUM(F2:F13) | G15: =SUM(G2:G13) | H15: =SUM(H2:H13) | I15: =IF(G15=0,"",F15/G15-1)
B17: Est. Net Income (after margin): | C17: =F15*Assumptions!C25

Sheet Goal Tracker
B1: Month | C1: Projected | D1: Actual | E1: Difference | F1: Cumulative Actual | G1: Cumulative Target | H1: On Track?
B2: January | C2: ='Monthly Projection'!F2 | D2: 0 | E2: =D2-C2 | F2: =SUM(D$2:D2) | G2: =SUM(C$2:C2) | H2: =IF(D2=0,"—",IF(F2>=G2,"✓ Yes","✗ Behind"))
B3: February | C3: ='Monthly Projection'!F3 | D3: 0 | E3: =D3-C3 | F3: =SUM(D$2:D3) | G3: =SUM(C$2:C3) | H3: =IF(D3=0,"—",IF(F3>=G3,"✓ Yes","✗ Behind"))
B4: March | C4: ='Monthly Projection'!F4 | D4: 0 | E4: =D4-C4 | F4: =SUM(D$2:D4) | G4: =SUM(C$2:C4) | H4: =IF(D4=0,"—",IF(F4>=G4,"✓ Yes","✗ Behind"))
B5: April | C5: ='Monthly Projection'!F5 | D5: 0 | E5: =D5-C5 | F5: =SUM(D$2:D5) | G5: =SUM(C$2:C5) | H5: =IF(D5=0,"—",IF(F5>=G5,"✓ Yes","✗ Behind"))
B6: May | C6: ='Monthly Projection'!F6 | D6: 0 | E6: =D6-C6 | F6: =SUM(D$2:D6) | G6: =SUM(C$2:C6) | H6: =IF(D6=0,"—",IF(F6>=G6,"✓ Yes","✗ Behind"))
B7: June | C7: ='Monthly Projection'!F7 | D7: 0 | E7: =D7-C7 | F7: =SUM(D$2:D7) | G7: =SUM(C$2:C7) | H7: =IF(D7=0,"—",IF(F7>=G7,"✓ Yes","✗ Behind"))
B8: July | C8: ='Monthly Projection'!F8 | D8: 0 | E8: =D8-C8 | F8: =SUM(D$2:D8) | G8: =SUM(C$2:C8) | H8: =IF(D8=0,"—",IF(F8>=G8,"✓ Yes","✗ Behind"))
B9: August | C9: ='Monthly Projection'!F9 | D9: 0 | E9: =D9-C9 | F9: =SUM(D$2:D9) | G9: =SUM(C$2:C9) | H9: =IF(D9=0,"—",IF(F9>=G9,"✓ Yes","✗ Behind"))
B10: September | C10: ='Monthly Projection'!F10 | D10: 0 | E10: =D10-C10 | F10: =SUM(D$2:D10) | G10: =SUM(C$2:C10) | H10: =IF(D10=0,"—",IF(F10>=G10,"✓ Yes","✗ Behind"))
B11: October | C11: ='Monthly Projection'!F11 | D11: 0 | E11: =D11-C11 | F11: =SUM(D$2:D11) | G11: =SUM(C$2:C11) | H11: =IF(D11=0,"—",IF(F11>=G11,"✓ Yes","✗ Behind"))
B12: November | C12: ='Monthly Projection'!F12 | D12: 0 | E12: =D12-C12 | F12: =SUM(D$2:D12) | G12: =SUM(C$2:C12) | H12: =IF(D12=0,"—",IF(F12>=G12,"✓ Yes","✗ Behind"))
B13: December | C13: ='Monthly Projection'!F13 | D13: 0 | E13: =D13-C13 | F13: =SUM(D$2:D13) | G13: =SUM(C$2:C13) | H13: =IF(D13=0,"—",IF(F13>=G13,"✓ Yes","✗ Behind"))

Sheet Income Milestones
B1: INCOME MILESTONES
B2: Monthly Target | C2: What It Represents | D2: Status
B3: 1000 | C3: Entry-level consistent freelancer | D3: =IF('Monthly Projection'!F15/12>=1000,"✓ Achieved","In Progress")
B4: 2500 | C4: Consistent part-time income | D4: =IF('Monthly Projection'!F15/12>=2500,"✓ Achieved","In Progress")
B5: 4000 | C5: Full-time freelance income replacement | D5: =IF('Monthly Projection'!F15/12>=4000,"✓ Achieved","In Progress")
B6: 5000 | C6: Strong freelance income | D6: =IF('Monthly Projection'!F15/12>=5000,"✓ Achieved","In Progress")
B7: 8000 | C7: Agency-level earnings | D7: =IF('Monthly Projection'!F15/12>=8000,"✓ Achieved","In Progress")
B8: 10000 | C8: Top-tier creative professional | D8: =IF('Monthly Projection'!F15/12>=10000,"✓ Achieved","In Progress")
B9: 15000 | C9: Studio-level revenue | D9: =IF('Monthly Projection'!F15/12>=15000,"✓ Achieved","In Progress")
